MANIFEST.in
README.md
requirements-dev.txt
requirements.txt
setup.cfg
setup.py
hyp/__init__.py
hyp/base.py
hyp/marshmallow.py
hyp/schematics.py
hyp.egg-info/PKG-INFO
hyp.egg-info/SOURCES.txt
hyp.egg-info/dependency_links.txt
hyp.egg-info/requires.txt
hyp.egg-info/top_level.txt