Metadata-Version: 1.1
Name: hyp
Version: 0.6.0
Summary: Partial JSON API implementation in Python on top of Schematics
Home-page: https://github.com/kalasjocke/hyp
Author: Joakim Ekberg
Author-email: jocke.ekberg@gmail.com
License: MIT
Platform: UNKNOWN
Classifier: Intended Audience :: Developers
Classifier: License :: OSI Approved :: MIT License
Classifier: Programming Language :: Python :: 2
Classifier: Programming Language :: Python :: 2.6
Classifier: Programming Language :: Python :: 2.7
Classifier: Programming Language :: Python :: 3
Classifier: Programming Language :: Python :: 3.3
Classifier: Programming Language :: Python :: 3.4
